Metadata-Version: 1.1
Name: hsccorpdamnitstupiddogman
Version: 0.0.1
Summary: A tool 
Home-page: UNKNOWN
Author: Ian Moffet and Arnav Nanduri
Author-email: arnanduri2006@gmail.com
License: MIT
Keywords: Hack
Platform: UNKNOWN
Classifier: Development Status :: 5 - Production/Stable
Classifier: Intended Audience :: Education
Classifier: Operating System :: Microsoft :: Windows :: Windows 10
Classifier: License :: OSI Approved :: MIT License
Classifier: Programming Language :: Python :: 3
